{
  "count": 10,
  "accounts": [
    {
      "user_id": "23054081",
      "username": "Boob.",
      "found_slurs": [
        "boob"
      ],
      "user_data": {
        "latest": {
          "rank": 3964011,
          "score": 1180,
          "username": "Boob.",
          "level": 0,
          "id": 23054081,
          "friend_images": {
            "micro": "https://www.kogstatic.com/gen_cache/avatar_images/mrchen_18x18.jpg",
            "small": "https://www.kogstatic.com/gen_cache/avatar_images/mrchen_46x46.jpg",
            "medium": "https://www.kogstatic.com/gen_cache/avatar_images/mrchen_64x64.jpg",
            "large": "https://www.kogstatic.com/gen_cache/avatar_images/mrchen_330x451.jpg"
          },
          "is_subscriber": 0
        },
        "pages": [
          9911
        ],
        "meta": {
          "batch": "3960001to3965000"
        }
      },
      "Credits": "Flagging accounts has been conducted by midweststatic @ discord <3"
    },
    {
      "user_id": "17834227",
      "username": "koks 6006",
      "found_slurs": [
        "boob"
      ],
      "user_data": {
        "latest": {
          "rank": 3989127,
          "score": 1170,
          "username": "koks 6006",
          "level": 0,
          "id": 17834227,
          "friend_images": {
            "micro": "https://www.kogstatic.com/gen_cache/3a/94/3a94e0b0-823e-4af0-94b9-f6a56f2a62d2_18x18.jpg",
            "small": "https://www.kogstatic.com/gen_cache/3a/94/3a94e0b0-823e-4af0-94b9-f6a56f2a62d2_46x46.jpg",
            "medium": "https://www.kogstatic.com/gen_cache/3a/94/3a94e0b0-823e-4af0-94b9-f6a56f2a62d2_64x64.jpg",
            "large": "https://www.kogstatic.com/gen_cache/3a/94/3a94e0b0-823e-4af0-94b9-f6a56f2a62d2_330x451.jpg"
          },
          "is_subscriber": 0
        },
        "pages": [
          9973
        ],
        "meta": {
          "batch": "3985001to3990000"
        }
      },
      "Credits": "Flagging accounts has been conducted by midweststatic @ discord <3"
    },
    {
      "user_id": "19967978",
      "username": "BOO8",
      "found_slurs": [
        "boob"
      ],
      "user_data": {
        "latest": {
          "rank": 4075290,
          "score": 1130,
          "username": "BOO8",
          "level": 0,
          "id": 19967978,
          "friend_images": {
            "micro": "https://www.kogstatic.com/gen_cache/avatar_images/kingoffire_18x18.jpg",
            "small": "https://www.kogstatic.com/gen_cache/avatar_images/kingoffire_46x46.jpg",
            "medium": "https://www.kogstatic.com/gen_cache/avatar_images/kingoffire_64x64.jpg",
            "large": "https://www.kogstatic.com/gen_cache/avatar_images/kingoffire_330x451.jpg"
          },
          "is_subscriber": 0
        },
        "pages": [
          10189
        ],
        "meta": {
          "batch": "4075001to4080000"
        }
      },
      "Credits": "Flagging accounts has been conducted by midweststatic @ discord <3"
    },
    {
      "user_id": "14406187",
      "username": "tazer boob",
      "found_slurs": [
        "boob"
      ],
      "user_data": {
        "latest": {
          "rank": 4161361,
          "score": 1091,
          "username": "tazer boob",
          "level": 0,
          "id": 14406187,
          "friend_images": {
            "micro": "https://www.kogstatic.com/gen_cache/avatar_images/panda_18x18.jpg",
            "small": "https://www.kogstatic.com/gen_cache/avatar_images/panda_46x46.jpg",
            "medium": "https://www.kogstatic.com/gen_cache/avatar_images/panda_64x64.jpg",
            "large": "https://www.kogstatic.com/gen_cache/avatar_images/panda_330x451.jpg"
          },
          "is_subscriber": 0
        },
        "pages": [
          10404
        ],
        "meta": {
          "batch": "4160001to4165000"
        }
      },
      "Credits": "Flagging accounts has been conducted by midweststatic @ discord <3"
    },
    {
      "user_id": "15768056",
      "username": "almost invisable panda boob",
      "found_slurs": [
        "boob"
      ],
      "user_data": {
        "latest": {
          "rank": 4198212,
          "score": 1080,
          "username": "almost invisable panda boob",
          "level": 0,
          "id": 15768056,
          "friend_images": {
            "micro": "https://www.kogstatic.com/gen_cache/avatar_images/panda_18x18.jpg",
            "small": "https://www.kogstatic.com/gen_cache/avatar_images/panda_46x46.jpg",
            "medium": "https://www.kogstatic.com/gen_cache/avatar_images/panda_64x64.jpg",
            "large": "https://www.kogstatic.com/gen_cache/avatar_images/panda_330x451.jpg"
          },
          "is_subscriber": 0
        },
        "pages": [
          10496
        ],
        "meta": {
          "batch": "4195001to4200000"
        }
      },
      "Credits": "Flagging accounts has been conducted by midweststatic @ discord <3"
    },
    {
      "user_id": "17958704",
      "username": "luci_8008",
      "found_slurs": [
        "boob"
      ],
      "user_data": {
        "latest": {
          "rank": 4204919,
          "score": 1075,
          "username": "luci_8008",
          "level": 0,
          "id": 17958704,
          "friend_images": {
            "micro": "https://www.kogstatic.com/gen_cache/avatar_images/girl_18x18.jpg",
            "small": "https://www.kogstatic.com/gen_cache/avatar_images/girl_46x46.jpg",
            "medium": "https://www.kogstatic.com/gen_cache/avatar_images/girl_64x64.jpg",
            "large": "https://www.kogstatic.com/gen_cache/avatar_images/girl_330x451.jpg"
          },
          "is_subscriber": 0
        },
        "pages": [
          10513
        ],
        "meta": {
          "batch": "4200001to4205000"
        }
      },
      "Credits": "Flagging accounts has been conducted by midweststatic @ discord <3"
    },
    {
      "user_id": "24343389",
      "username": "Julio 8008",
      "found_slurs": [
        "boob"
      ],
      "user_data": {
        "latest": {
          "rank": 4289890,
          "score": 1040,
          "username": "Julio 8008",
          "level": 0,
          "id": 24343389,
          "friend_images": {
            "micro": "https://www.kogstatic.com/gen_cache/avatar_images/kingoffire_18x18.jpg",
            "small": "https://www.kogstatic.com/gen_cache/avatar_images/kingoffire_46x46.jpg",
            "medium": "https://www.kogstatic.com/gen_cache/avatar_images/kingoffire_64x64.jpg",
            "large": "https://www.kogstatic.com/gen_cache/avatar_images/kingoffire_330x451.jpg"
          },
          "is_subscriber": 0
        },
        "pages": [
          10725
        ],
        "meta": {
          "batch": "4285001to4290000"
        }
      },
      "Credits": "Flagging accounts has been conducted by midweststatic @ discord <3"
    },
    {
      "user_id": "15707043",
      "username": "beeb boob-_-",
      "found_slurs": [
        "boob"
      ],
      "user_data": {
        "latest": {
          "rank": 4379498,
          "score": 1010,
          "username": "beeb boob-_-",
          "level": 0,
          "id": 15707043,
          "friend_images": {
            "micro": "https://www.kogstatic.com/gen_cache/avatar_images/robot_18x18.jpg",
            "small": "https://www.kogstatic.com/gen_cache/avatar_images/robot_46x46.jpg",
            "medium": "https://www.kogstatic.com/gen_cache/avatar_images/robot_64x64.jpg",
            "large": "https://www.kogstatic.com/gen_cache/avatar_images/robot_330x451.jpg"
          },
          "is_subscriber": 0
        },
        "pages": [
          10949
        ],
        "meta": {
          "batch": "4375001to4380000"
        }
      },
      "Credits": "Flagging accounts has been conducted by midweststatic @ discord <3"
    },
    {
      "user_id": "670367414",
      "username": "almendra.8008",
      "found_slurs": [
        "boob"
      ],
      "user_data": {
        "latest": {
          "rank": 4392448,
          "score": 1000,
          "username": "almendra.8008",
          "level": 0,
          "id": 670367414,
          "friend_images": {
            "original": "https://www.kogstatic.com/gen_images/bc/1b/bc1bff4c-783c-4fcc-805c-455e7df7e4e4.png",
            "micro": "https://www.kogstatic.com/gen_cache/bc/1b/bc1bff4c-783c-4fcc-805c-455e7df7e4e4_18x18.png",
            "small": "https://www.kogstatic.com/gen_cache/bc/1b/bc1bff4c-783c-4fcc-805c-455e7df7e4e4_46x46.png",
            "medium": "https://www.kogstatic.com/gen_cache/bc/1b/bc1bff4c-783c-4fcc-805c-455e7df7e4e4_64x64.png",
            "large": "https://www.kogstatic.com/gen_cache/bc/1b/bc1bff4c-783c-4fcc-805c-455e7df7e4e4_330x451.png"
          },
          "is_subscriber": 0
        },
        "pages": [
          10982
        ],
        "meta": {
          "batch": "4390001to4395000"
        }
      },
      "Credits": "Flagging accounts has been conducted by midweststatic @ discord <3"
    },
    {
      "user_id": "20203564",
      "username": "Bierith pacheco boob",
      "found_slurs": [
        "boob"
      ],
      "user_data": {
        "latest": {
          "rank": 4456576,
          "score": 980,
          "username": "Bierith pacheco boob",
          "level": 0,
          "id": 20203564,
          "friend_images": {
            "micro": "https://www.kogstatic.com/placeholder/blockboy_micro_18x18.jpg",
            "small": "https://www.kogstatic.com/placeholder/blockboy_small_46x46.jpg",
            "medium": "https://www.kogstatic.com/placeholder/blockboy_medium_64x64.jpg",
            "large": "https://www.kogstatic.com/placeholder/blockboy_large_330x451.jpg"
          },
          "is_subscriber": 0
        },
        "pages": [
          11142
        ],
        "meta": {
          "batch": "4455001to4460000"
        }
      },
      "Credits": "Flagging accounts has been conducted by midweststatic @ discord <3"
    }
  ]
}
