{
  "count": 34,
  "accounts": [
    {
      "user_id": "22520186",
      "username": "1111116666666776687567",
      "normalized_username": "1111116666666776687567",
      "suspicion_score": 6,
      "patterns": {
        "ends_with_numbers": true,
        "contains_bot_keywords": false,
        "repeated_patterns": true,
        "sequential_numbers": true,
        "many_numbers": true,
        "special_word_combos": false,
        "generic_names": false,
        "consecutive_duplicates": true
      },
      "user_data": {
        "latest": {
          "rank": 1684362,
          "score": 3967,
          "username": "1111116666666776687567",
          "level": 0,
          "id": 22520186,
          "friend_images": {
            "micro": "https://www.kogstatic.com/gen_cache/avatar_images/girl_18x18.jpg",
            "small": "https://www.kogstatic.com/gen_cache/avatar_images/girl_46x46.jpg",
            "medium": "https://www.kogstatic.com/gen_cache/avatar_images/girl_64x64.jpg",
            "large": "https://www.kogstatic.com/gen_cache/avatar_images/girl_330x451.jpg"
          },
          "is_subscriber": 0
        },
        "pages": [
          4211
        ],
        "meta": {
          "batch": "1680001to1685000"
        }
      }
    },
    {
      "user_id": "15569247",
      "username": "111111111111111111222222",
      "normalized_username": "111111111111111111222222",
      "suspicion_score": 4,
      "patterns": {
        "ends_with_numbers": true,
        "contains_bot_keywords": false,
        "repeated_patterns": true,
        "sequential_numbers": false,
        "many_numbers": true,
        "special_word_combos": false,
        "generic_names": false,
        "consecutive_duplicates": true
      },
      "user_data": {
        "latest": {
          "rank": 1686993,
          "score": 3960,
          "username": "111111111111111111222222",
          "level": 0,
          "id": 15569247,
          "friend_images": {
            "micro": "https://www.kogstatic.com/gen_cache/avatar_images/kingoffire_18x18.jpg",
            "small": "https://www.kogstatic.com/gen_cache/avatar_images/kingoffire_46x46.jpg",
            "medium": "https://www.kogstatic.com/gen_cache/avatar_images/kingoffire_64x64.jpg",
            "large": "https://www.kogstatic.com/gen_cache/avatar_images/kingoffire_330x451.jpg"
          },
          "is_subscriber": 0
        },
        "pages": [
          4218
        ],
        "meta": {
          "batch": "1685001to1690000"
        }
      }
    },
    {
      "user_id": "19397226",
      "username": "_111111_",
      "normalized_username": "_111111_",
      "suspicion_score": 3,
      "patterns": {
        "ends_with_numbers": false,
        "contains_bot_keywords": false,
        "repeated_patterns": true,
        "sequential_numbers": false,
        "many_numbers": true,
        "special_word_combos": false,
        "generic_names": false,
        "consecutive_duplicates": true
      },
      "user_data": {
        "latest": {
          "rank": 1692921,
          "score": 3940,
          "username": "_111111_",
          "level": 0,
          "id": 19397226,
          "friend_images": {
            "micro": "https://www.kogstatic.com/gen_cache/ba/6d/ba6d8d75-5c78-4747-a3d1-a785eec18fbf_18x18.jpg",
            "small": "https://www.kogstatic.com/gen_cache/ba/6d/ba6d8d75-5c78-4747-a3d1-a785eec18fbf_46x46.jpg",
            "medium": "https://www.kogstatic.com/gen_cache/ba/6d/ba6d8d75-5c78-4747-a3d1-a785eec18fbf_64x64.jpg",
            "large": "https://www.kogstatic.com/gen_cache/ba/6d/ba6d8d75-5c78-4747-a3d1-a785eec18fbf_330x451.jpg"
          },
          "is_subscriber": 0
        },
        "pages": [
          4233
        ],
        "meta": {
          "batch": "1690001to1695000"
        }
      }
    },
    {
      "user_id": "50719387",
      "username": "111111118888888899999900",
      "normalized_username": "111111118888888899999900",
      "suspicion_score": 4,
      "patterns": {
        "ends_with_numbers": true,
        "contains_bot_keywords": false,
        "repeated_patterns": true,
        "sequential_numbers": false,
        "many_numbers": true,
        "special_word_combos": false,
        "generic_names": false,
        "consecutive_duplicates": true
      },
      "user_data": {
        "latest": {
          "rank": 1697047,
          "score": 3928,
          "username": "111111118888888899999900",
          "level": 0,
          "id": 50719387,
          "friend_images": {
            "micro": "https://www.kogstatic.com/placeholder/blockboy_micro_18x18.jpg",
            "small": "https://www.kogstatic.com/placeholder/blockboy_small_46x46.jpg",
            "medium": "https://www.kogstatic.com/placeholder/blockboy_medium_64x64.jpg",
            "large": "https://www.kogstatic.com/placeholder/blockboy_large_330x451.jpg"
          },
          "is_subscriber": 0
        },
        "pages": [
          4243
        ],
        "meta": {
          "batch": "1695001to1700000"
        }
      }
    },
    {
      "user_id": "18242617",
      "username": "111111111133333333",
      "normalized_username": "111111111133333333",
      "suspicion_score": 4,
      "patterns": {
        "ends_with_numbers": true,
        "contains_bot_keywords": false,
        "repeated_patterns": true,
        "sequential_numbers": false,
        "many_numbers": true,
        "special_word_combos": false,
        "generic_names": false,
        "consecutive_duplicates": true
      },
      "user_data": {
        "latest": {
          "rank": 1699588,
          "score": 3920,
          "username": "111111111133333333",
          "level": 0,
          "id": 18242617,
          "friend_images": {
            "micro": "https://www.kogstatic.com/gen_cache/ef/40/ef40f250-06c9-41a2-b80b-b9cd764e9ea7_18x18.jpg",
            "small": "https://www.kogstatic.com/gen_cache/ef/40/ef40f250-06c9-41a2-b80b-b9cd764e9ea7_46x46.jpg",
            "medium": "https://www.kogstatic.com/gen_cache/ef/40/ef40f250-06c9-41a2-b80b-b9cd764e9ea7_64x64.jpg",
            "large": "https://www.kogstatic.com/gen_cache/ef/40/ef40f250-06c9-41a2-b80b-b9cd764e9ea7_330x451.jpg"
          },
          "is_subscriber": 0
        },
        "pages": [
          4249
        ],
        "meta": {
          "batch": "1695001to1700000"
        }
      }
    },
    {
      "user_id": "10804616",
      "username": "+++111+++111+++111+++",
      "normalized_username": "111111111",
      "suspicion_score": 3,
      "patterns": {
        "ends_with_numbers": false,
        "contains_bot_keywords": false,
        "repeated_patterns": true,
        "sequential_numbers": false,
        "many_numbers": true,
        "special_word_combos": false,
        "generic_names": false,
        "consecutive_duplicates": true
      },
      "user_data": {
        "latest": {
          "rank": 1732258,
          "score": 3823,
          "username": "+++111+++111+++111+++",
          "level": 0,
          "id": 10804616,
          "friend_images": {
            "micro": "https://www.kogstatic.com/placeholder/blockboy_micro_18x18.jpg",
            "small": "https://www.kogstatic.com/placeholder/blockboy_small_46x46.jpg",
            "medium": "https://www.kogstatic.com/placeholder/blockboy_medium_64x64.jpg",
            "large": "https://www.kogstatic.com/placeholder/blockboy_large_330x451.jpg"
          },
          "is_subscriber": 0
        },
        "pages": [
          4331
        ],
        "meta": {
          "batch": "1730001to1735000"
        }
      }
    },
    {
      "user_id": "51106266",
      "username": "1111111112078",
      "normalized_username": "1111111112078",
      "suspicion_score": 4,
      "patterns": {
        "ends_with_numbers": true,
        "contains_bot_keywords": false,
        "repeated_patterns": true,
        "sequential_numbers": false,
        "many_numbers": true,
        "special_word_combos": false,
        "generic_names": false,
        "consecutive_duplicates": true
      },
      "user_data": {
        "latest": {
          "rank": 1737864,
          "score": 3808,
          "username": "1111111112078",
          "level": 0,
          "id": 51106266,
          "friend_images": {
            "micro": "https://www.kogstatic.com/gen_cache/avatar_images/panda_18x18.jpg",
            "small": "https://www.kogstatic.com/gen_cache/avatar_images/panda_46x46.jpg",
            "medium": "https://www.kogstatic.com/gen_cache/avatar_images/panda_64x64.jpg",
            "large": "https://www.kogstatic.com/gen_cache/avatar_images/panda_330x451.jpg"
          },
          "is_subscriber": 0
        },
        "pages": [
          4345
        ],
        "meta": {
          "batch": "1735001to1740000"
        }
      }
    },
    {
      "user_id": "14827125",
      "username": "111111112212",
      "normalized_username": "111111112212",
      "suspicion_score": 4,
      "patterns": {
        "ends_with_numbers": true,
        "contains_bot_keywords": false,
        "repeated_patterns": true,
        "sequential_numbers": false,
        "many_numbers": true,
        "special_word_combos": false,
        "generic_names": false,
        "consecutive_duplicates": true
      },
      "user_data": {
        "latest": {
          "rank": 1742319,
          "score": 3795,
          "username": "111111112212",
          "level": 0,
          "id": 14827125,
          "friend_images": {
            "micro": "https://www.kogstatic.com/gen_cache/avatar_images/panda_18x18.jpg",
            "small": "https://www.kogstatic.com/gen_cache/avatar_images/panda_46x46.jpg",
            "medium": "https://www.kogstatic.com/gen_cache/avatar_images/panda_64x64.jpg",
            "large": "https://www.kogstatic.com/gen_cache/avatar_images/panda_330x451.jpg"
          },
          "is_subscriber": 0
        },
        "pages": [
          4356
        ],
        "meta": {
          "batch": "1740001to1745000"
        }
      }
    },
    {
      "user_id": "18697994",
      "username": "111111-9",
      "normalized_username": "111111-9",
      "suspicion_score": 3,
      "patterns": {
        "ends_with_numbers": false,
        "contains_bot_keywords": false,
        "repeated_patterns": true,
        "sequential_numbers": false,
        "many_numbers": true,
        "special_word_combos": false,
        "generic_names": false,
        "consecutive_duplicates": true
      },
      "user_data": {
        "latest": {
          "rank": 1763739,
          "score": 3735,
          "username": "111111-9",
          "level": 0,
          "id": 18697994,
          "friend_images": {
            "micro": "https://www.kogstatic.com/placeholder/blockboy_micro_18x18.jpg",
            "small": "https://www.kogstatic.com/placeholder/blockboy_small_46x46.jpg",
            "medium": "https://www.kogstatic.com/placeholder/blockboy_medium_64x64.jpg",
            "large": "https://www.kogstatic.com/placeholder/blockboy_large_330x451.jpg"
          },
          "is_subscriber": 0
        },
        "pages": [
          4410
        ],
        "meta": {
          "batch": "1760001to1765000"
        }
      }
    },
    {
      "user_id": "667011770",
      "username": "11111199999999995555555",
      "normalized_username": "11111199999999995555555",
      "suspicion_score": 4,
      "patterns": {
        "ends_with_numbers": true,
        "contains_bot_keywords": false,
        "repeated_patterns": true,
        "sequential_numbers": false,
        "many_numbers": true,
        "special_word_combos": false,
        "generic_names": false,
        "consecutive_duplicates": true
      },
      "user_data": {
        "latest": {
          "rank": 1790400,
          "score": 3662,
          "username": "11111199999999995555555",
          "level": 0,
          "id": 667011770,
          "friend_images": {
            "micro": "https://www.kogstatic.com/placeholder/blockboy_micro_18x18.jpg",
            "small": "https://www.kogstatic.com/placeholder/blockboy_small_46x46.jpg",
            "medium": "https://www.kogstatic.com/placeholder/blockboy_medium_64x64.jpg",
            "large": "https://www.kogstatic.com/placeholder/blockboy_large_330x451.jpg"
          },
          "is_subscriber": 0
        },
        "pages": [
          4476
        ],
        "meta": {
          "batch": "1790001to1795000"
        }
      }
    },
    {
      "user_id": "20864383",
      "username": "111111111111111111154545543",
      "normalized_username": "111111111111111111154545543",
      "suspicion_score": 6,
      "patterns": {
        "ends_with_numbers": true,
        "contains_bot_keywords": false,
        "repeated_patterns": true,
        "sequential_numbers": true,
        "many_numbers": true,
        "special_word_combos": false,
        "generic_names": false,
        "consecutive_duplicates": true
      },
      "user_data": {
        "latest": {
          "rank": 1829297,
          "score": 3563,
          "username": "111111111111111111154545543",
          "level": 0,
          "id": 20864383,
          "friend_images": {
            "micro": "https://www.kogstatic.com/gen_cache/avatar_images/kingoffire_18x18.jpg",
            "small": "https://www.kogstatic.com/gen_cache/avatar_images/kingoffire_46x46.jpg",
            "medium": "https://www.kogstatic.com/gen_cache/avatar_images/kingoffire_64x64.jpg",
            "large": "https://www.kogstatic.com/gen_cache/avatar_images/kingoffire_330x451.jpg"
          },
          "is_subscriber": 0
        },
        "pages": [
          4574
        ],
        "meta": {
          "batch": "1825001to1830000"
        }
      }
    },
    {
      "user_id": "17074415",
      "username": "11111111000000000",
      "normalized_username": "11111111000000000",
      "suspicion_score": 4,
      "patterns": {
        "ends_with_numbers": true,
        "contains_bot_keywords": false,
        "repeated_patterns": true,
        "sequential_numbers": false,
        "many_numbers": true,
        "special_word_combos": false,
        "generic_names": false,
        "consecutive_duplicates": true
      },
      "user_data": {
        "latest": {
          "rank": 1835008,
          "score": 3550,
          "username": "11111111000000000",
          "level": 0,
          "id": 17074415,
          "friend_images": {
            "micro": "https://www.kogstatic.com/gen_cache/avatar_images/panda_18x18.jpg",
            "small": "https://www.kogstatic.com/gen_cache/avatar_images/panda_46x46.jpg",
            "medium": "https://www.kogstatic.com/gen_cache/avatar_images/panda_64x64.jpg",
            "large": "https://www.kogstatic.com/gen_cache/avatar_images/panda_330x451.jpg"
          },
          "is_subscriber": 0
        },
        "pages": [
          4588
        ],
        "meta": {
          "batch": "1835001to1840000"
        }
      }
    },
    {
      "user_id": "17878728",
      "username": "1111111111111111111111236",
      "normalized_username": "1111111111111111111111236",
      "suspicion_score": 6,
      "patterns": {
        "ends_with_numbers": true,
        "contains_bot_keywords": false,
        "repeated_patterns": true,
        "sequential_numbers": true,
        "many_numbers": true,
        "special_word_combos": false,
        "generic_names": false,
        "consecutive_duplicates": true
      },
      "user_data": {
        "latest": {
          "rank": 1850877,
          "score": 3510,
          "username": "1111111111111111111111236",
          "level": 0,
          "id": 17878728,
          "friend_images": {
            "micro": "https://www.kogstatic.com/gen_cache/avatar_images/panda_18x18.jpg",
            "small": "https://www.kogstatic.com/gen_cache/avatar_images/panda_46x46.jpg",
            "medium": "https://www.kogstatic.com/gen_cache/avatar_images/panda_64x64.jpg",
            "large": "https://www.kogstatic.com/gen_cache/avatar_images/panda_330x451.jpg"
          },
          "is_subscriber": 0
        },
        "pages": [
          4628
        ],
        "meta": {
          "batch": "1850001to1855000"
        }
      }
    },
    {
      "user_id": "16433991",
      "username": "111111222223331234",
      "normalized_username": "111111222223331234",
      "suspicion_score": 6,
      "patterns": {
        "ends_with_numbers": true,
        "contains_bot_keywords": false,
        "repeated_patterns": true,
        "sequential_numbers": true,
        "many_numbers": true,
        "special_word_combos": false,
        "generic_names": false,
        "consecutive_duplicates": true
      },
      "user_data": {
        "latest": {
          "rank": 1895874,
          "score": 3400,
          "username": "111111222223331234",
          "level": 0,
          "id": 16433991,
          "friend_images": {
            "micro": "https://www.kogstatic.com/gen_cache/avatar_images/robot_18x18.jpg",
            "small": "https://www.kogstatic.com/gen_cache/avatar_images/robot_46x46.jpg",
            "medium": "https://www.kogstatic.com/gen_cache/avatar_images/robot_64x64.jpg",
            "large": "https://www.kogstatic.com/gen_cache/avatar_images/robot_330x451.jpg"
          },
          "is_subscriber": 0
        },
        "pages": [
          4740
        ],
        "meta": {
          "batch": "1895001to1900000"
        }
      }
    },
    {
      "user_id": "19336700",
      "username": "111111111111111125",
      "normalized_username": "111111111111111125",
      "suspicion_score": 4,
      "patterns": {
        "ends_with_numbers": true,
        "contains_bot_keywords": false,
        "repeated_patterns": true,
        "sequential_numbers": false,
        "many_numbers": true,
        "special_word_combos": false,
        "generic_names": false,
        "consecutive_duplicates": true
      },
      "user_data": {
        "latest": {
          "rank": 1897319,
          "score": 3395,
          "username": "111111111111111125",
          "level": 0,
          "id": 19336700,
          "friend_images": {
            "micro": "https://www.kogstatic.com/gen_cache/fc/ce/fcce5031-a7b1-46a2-ae7c-43670b756fbc_18x18.jpg",
            "small": "https://www.kogstatic.com/gen_cache/fc/ce/fcce5031-a7b1-46a2-ae7c-43670b756fbc_46x46.jpg",
            "medium": "https://www.kogstatic.com/gen_cache/fc/ce/fcce5031-a7b1-46a2-ae7c-43670b756fbc_64x64.jpg",
            "large": "https://www.kogstatic.com/gen_cache/fc/ce/fcce5031-a7b1-46a2-ae7c-43670b756fbc_330x451.jpg"
          },
          "is_subscriber": 0
        },
        "pages": [
          4744
        ],
        "meta": {
          "batch": "1895001to1900000"
        }
      }
    },
    {
      "user_id": "14898541",
      "username": "1111112222222223",
      "normalized_username": "1111112222222223",
      "suspicion_score": 4,
      "patterns": {
        "ends_with_numbers": true,
        "contains_bot_keywords": false,
        "repeated_patterns": true,
        "sequential_numbers": false,
        "many_numbers": true,
        "special_word_combos": false,
        "generic_names": false,
        "consecutive_duplicates": true
      },
      "user_data": {
        "latest": {
          "rank": 1898008,
          "score": 3393,
          "username": "1111112222222223",
          "level": 0,
          "id": 14898541,
          "friend_images": {
            "micro": "https://www.kogstatic.com/gen_cache/dc/40/dc404da30eaf46a2aa48ce0f3d657c6d_18x18.jpg",
            "small": "https://www.kogstatic.com/gen_cache/dc/40/dc404da30eaf46a2aa48ce0f3d657c6d_46x46.jpg",
            "medium": "https://www.kogstatic.com/gen_cache/dc/40/dc404da30eaf46a2aa48ce0f3d657c6d_64x64.jpg",
            "large": "https://www.kogstatic.com/gen_cache/dc/40/dc404da30eaf46a2aa48ce0f3d657c6d_330x451.jpg"
          },
          "is_subscriber": 0
        },
        "pages": [
          4746
        ],
        "meta": {
          "batch": "1895001to1900000"
        }
      }
    },
    {
      "user_id": "22537627",
      "username": "-11111111-",
      "normalized_username": "-11111111-",
      "suspicion_score": 3,
      "patterns": {
        "ends_with_numbers": false,
        "contains_bot_keywords": false,
        "repeated_patterns": true,
        "sequential_numbers": false,
        "many_numbers": true,
        "special_word_combos": false,
        "generic_names": false,
        "consecutive_duplicates": true
      },
      "user_data": {
        "latest": {
          "rank": 1903401,
          "score": 3380,
          "username": "-11111111-",
          "level": 0,
          "id": 22537627,
          "friend_images": {
            "micro": "https://www.kogstatic.com/gen_cache/avatar_images/girl_18x18.jpg",
            "small": "https://www.kogstatic.com/gen_cache/avatar_images/girl_46x46.jpg",
            "medium": "https://www.kogstatic.com/gen_cache/avatar_images/girl_64x64.jpg",
            "large": "https://www.kogstatic.com/gen_cache/avatar_images/girl_330x451.jpg"
          },
          "is_subscriber": 0
        },
        "pages": [
          4759
        ],
        "meta": {
          "batch": "1900001to1905000"
        }
      }
    },
    {
      "user_id": "9987239",
      "username": "11111113",
      "normalized_username": "11111113",
      "suspicion_score": 4,
      "patterns": {
        "ends_with_numbers": true,
        "contains_bot_keywords": false,
        "repeated_patterns": true,
        "sequential_numbers": false,
        "many_numbers": true,
        "special_word_combos": false,
        "generic_names": false,
        "consecutive_duplicates": true
      },
      "user_data": {
        "latest": {
          "rank": 1906080,
          "score": 3374,
          "username": "11111113",
          "level": 0,
          "id": 9987239,
          "friend_images": {
            "micro": "https://www.kogstatic.com/placeholder/blockboy_micro_18x18.jpg",
            "small": "https://www.kogstatic.com/placeholder/blockboy_small_46x46.jpg",
            "medium": "https://www.kogstatic.com/placeholder/blockboy_medium_64x64.jpg",
            "large": "https://www.kogstatic.com/placeholder/blockboy_large_330x451.jpg"
          },
          "is_subscriber": 0
        },
        "pages": [
          4766
        ],
        "meta": {
          "batch": "1905001to1910000"
        }
      }
    },
    {
      "user_id": "16189786",
      "username": "11111111111111111112211",
      "normalized_username": "11111111111111111112211",
      "suspicion_score": 4,
      "patterns": {
        "ends_with_numbers": true,
        "contains_bot_keywords": false,
        "repeated_patterns": true,
        "sequential_numbers": false,
        "many_numbers": true,
        "special_word_combos": false,
        "generic_names": false,
        "consecutive_duplicates": true
      },
      "user_data": {
        "latest": {
          "rank": 1970025,
          "score": 3230,
          "username": "11111111111111111112211",
          "level": 0,
          "id": 16189786,
          "friend_images": {
            "micro": "https://www.kogstatic.com/gen_cache/40/49/404900e1-fea8-4722-8931-8ff957825838_18x18.jpg",
            "small": "https://www.kogstatic.com/gen_cache/40/49/404900e1-fea8-4722-8931-8ff957825838_46x46.jpg",
            "medium": "https://www.kogstatic.com/gen_cache/40/49/404900e1-fea8-4722-8931-8ff957825838_64x64.jpg",
            "large": "https://www.kogstatic.com/gen_cache/40/49/404900e1-fea8-4722-8931-8ff957825838_330x451.jpg"
          },
          "is_subscriber": 0
        },
        "pages": [
          4926
        ],
        "meta": {
          "batch": "1970001to1975000"
        }
      }
    },
    {
      "user_id": "24713974",
      "username": "111111777777",
      "normalized_username": "111111777777",
      "suspicion_score": 4,
      "patterns": {
        "ends_with_numbers": true,
        "contains_bot_keywords": false,
        "repeated_patterns": true,
        "sequential_numbers": false,
        "many_numbers": true,
        "special_word_combos": false,
        "generic_names": false,
        "consecutive_duplicates": true
      },
      "user_data": {
        "latest": {
          "rank": 1975069,
          "score": 3219,
          "username": "111111777777",
          "level": 0,
          "id": 24713974,
          "friend_images": {
            "micro": "https://www.kogstatic.com/placeholder/blockboy_micro_18x18.jpg",
            "small": "https://www.kogstatic.com/placeholder/blockboy_small_46x46.jpg",
            "medium": "https://www.kogstatic.com/placeholder/blockboy_medium_64x64.jpg",
            "large": "https://www.kogstatic.com/placeholder/blockboy_large_330x451.jpg"
          },
          "is_subscriber": 0
        },
        "pages": [
          4938
        ],
        "meta": {
          "batch": "1975001to1980000"
        }
      }
    },
    {
      "user_id": "17211761",
      "username": "11111111111111111133333",
      "normalized_username": "11111111111111111133333",
      "suspicion_score": 4,
      "patterns": {
        "ends_with_numbers": true,
        "contains_bot_keywords": false,
        "repeated_patterns": true,
        "sequential_numbers": false,
        "many_numbers": true,
        "special_word_combos": false,
        "generic_names": false,
        "consecutive_duplicates": true
      },
      "user_data": {
        "latest": {
          "rank": 1978905,
          "score": 3210,
          "username": "11111111111111111133333",
          "level": 0,
          "id": 17211761,
          "friend_images": {
            "micro": "https://www.kogstatic.com/gen_cache/avatar_images/mrchen_18x18.jpg",
            "small": "https://www.kogstatic.com/gen_cache/avatar_images/mrchen_46x46.jpg",
            "medium": "https://www.kogstatic.com/gen_cache/avatar_images/mrchen_64x64.jpg",
            "large": "https://www.kogstatic.com/gen_cache/avatar_images/mrchen_330x451.jpg"
          },
          "is_subscriber": 0
        },
        "pages": [
          4948
        ],
        "meta": {
          "batch": "1975001to1980000"
        }
      }
    },
    {
      "user_id": "9970236",
      "username": "11111111111111111111111122222",
      "normalized_username": "11111111111111111111111122222",
      "suspicion_score": 4,
      "patterns": {
        "ends_with_numbers": true,
        "contains_bot_keywords": false,
        "repeated_patterns": true,
        "sequential_numbers": false,
        "many_numbers": true,
        "special_word_combos": false,
        "generic_names": false,
        "consecutive_duplicates": true
      },
      "user_data": {
        "latest": {
          "rank": 2017423,
          "score": 3126,
          "username": "11111111111111111111111122222",
          "level": 0,
          "id": 9970236,
          "friend_images": {
            "micro": "https://www.kogstatic.com/placeholder/blockboy_micro_18x18.jpg",
            "small": "https://www.kogstatic.com/placeholder/blockboy_small_46x46.jpg",
            "medium": "https://www.kogstatic.com/placeholder/blockboy_medium_64x64.jpg",
            "large": "https://www.kogstatic.com/placeholder/blockboy_large_330x451.jpg"
          },
          "is_subscriber": 0
        },
        "pages": [
          5044
        ],
        "meta": {
          "batch": "2015001to2020000"
        }
      }
    },
    {
      "user_id": "19487612",
      "username": "111111154635",
      "normalized_username": "111111154635",
      "suspicion_score": 4,
      "patterns": {
        "ends_with_numbers": true,
        "contains_bot_keywords": false,
        "repeated_patterns": true,
        "sequential_numbers": false,
        "many_numbers": true,
        "special_word_combos": false,
        "generic_names": false,
        "consecutive_duplicates": true
      },
      "user_data": {
        "latest": {
          "rank": 2020426,
          "score": 3120,
          "username": "111111154635",
          "level": 0,
          "id": 19487612,
          "friend_images": {
            "micro": "https://www.kogstatic.com/gen_cache/avatar_images/girl_18x18.jpg",
            "small": "https://www.kogstatic.com/gen_cache/avatar_images/girl_46x46.jpg",
            "medium": "https://www.kogstatic.com/gen_cache/avatar_images/girl_64x64.jpg",
            "large": "https://www.kogstatic.com/gen_cache/avatar_images/girl_330x451.jpg"
          },
          "is_subscriber": 0
        },
        "pages": [
          5052
        ],
        "meta": {
          "batch": "2020001to2025000"
        }
      }
    },
    {
      "user_id": "20556331",
      "username": "111111119999999955555555",
      "normalized_username": "111111119999999955555555",
      "suspicion_score": 4,
      "patterns": {
        "ends_with_numbers": true,
        "contains_bot_keywords": false,
        "repeated_patterns": true,
        "sequential_numbers": false,
        "many_numbers": true,
        "special_word_combos": false,
        "generic_names": false,
        "consecutive_duplicates": true
      },
      "user_data": {
        "latest": {
          "rank": 2031956,
          "score": 3096,
          "username": "111111119999999955555555",
          "level": 0,
          "id": 20556331,
          "friend_images": {
            "micro": "https://www.kogstatic.com/gen_cache/avatar_images/robot_18x18.jpg",
            "small": "https://www.kogstatic.com/gen_cache/avatar_images/robot_46x46.jpg",
            "medium": "https://www.kogstatic.com/gen_cache/avatar_images/robot_64x64.jpg",
            "large": "https://www.kogstatic.com/gen_cache/avatar_images/robot_330x451.jpg"
          },
          "is_subscriber": 0
        },
        "pages": [
          5080
        ],
        "meta": {
          "batch": "2030001to2035000"
        }
      }
    },
    {
      "user_id": "11635533",
      "username": "11111111222222",
      "normalized_username": "11111111222222",
      "suspicion_score": 4,
      "patterns": {
        "ends_with_numbers": true,
        "contains_bot_keywords": false,
        "repeated_patterns": true,
        "sequential_numbers": false,
        "many_numbers": true,
        "special_word_combos": false,
        "generic_names": false,
        "consecutive_duplicates": true
      },
      "user_data": {
        "latest": {
          "rank": 2036264,
          "score": 3089,
          "username": "11111111222222",
          "level": 0,
          "id": 11635533,
          "friend_images": {
            "micro": "https://www.kogstatic.com/placeholder/blockboy_micro_18x18.jpg",
            "small": "https://www.kogstatic.com/placeholder/blockboy_small_46x46.jpg",
            "medium": "https://www.kogstatic.com/placeholder/blockboy_medium_64x64.jpg",
            "large": "https://www.kogstatic.com/placeholder/blockboy_large_330x451.jpg"
          },
          "is_subscriber": 0
        },
        "pages": [
          5091
        ],
        "meta": {
          "batch": "2035001to2040000"
        }
      }
    },
    {
      "user_id": "15009669",
      "username": "11111113456178452307613434133",
      "normalized_username": "11111113456178452307613434133",
      "suspicion_score": 6,
      "patterns": {
        "ends_with_numbers": true,
        "contains_bot_keywords": false,
        "repeated_patterns": true,
        "sequential_numbers": true,
        "many_numbers": true,
        "special_word_combos": false,
        "generic_names": false,
        "consecutive_duplicates": true
      },
      "user_data": {
        "latest": {
          "rank": 2043151,
          "score": 3072,
          "username": "11111113456178452307613434133",
          "level": 0,
          "id": 15009669,
          "friend_images": {
            "micro": "https://www.kogstatic.com/gen_cache/1b/cf/1bcf80ca0ed04541acc14fc1d502ab13_18x18.jpg",
            "small": "https://www.kogstatic.com/gen_cache/1b/cf/1bcf80ca0ed04541acc14fc1d502ab13_46x46.jpg",
            "medium": "https://www.kogstatic.com/gen_cache/1b/cf/1bcf80ca0ed04541acc14fc1d502ab13_64x64.jpg",
            "large": "https://www.kogstatic.com/gen_cache/1b/cf/1bcf80ca0ed04541acc14fc1d502ab13_330x451.jpg"
          },
          "is_subscriber": 0
        },
        "pages": [
          5108
        ],
        "meta": {
          "batch": "2040001to2045000"
        }
      }
    },
    {
      "user_id": "17312215",
      "username": "111111111111111@2222222222",
      "normalized_username": "111111111111111@2222222222",
      "suspicion_score": 4,
      "patterns": {
        "ends_with_numbers": true,
        "contains_bot_keywords": false,
        "repeated_patterns": true,
        "sequential_numbers": false,
        "many_numbers": true,
        "special_word_combos": false,
        "generic_names": false,
        "consecutive_duplicates": true
      },
      "user_data": {
        "latest": {
          "rank": 2050054,
          "score": 3060,
          "username": "111111111111111@2222222222",
          "level": 0,
          "id": 17312215,
          "friend_images": {
            "micro": "https://www.kogstatic.com/gen_cache/avatar_images/robot_18x18.jpg",
            "small": "https://www.kogstatic.com/gen_cache/avatar_images/robot_46x46.jpg",
            "medium": "https://www.kogstatic.com/gen_cache/avatar_images/robot_64x64.jpg",
            "large": "https://www.kogstatic.com/gen_cache/avatar_images/robot_330x451.jpg"
          },
          "is_subscriber": 0
        },
        "pages": [
          5126
        ],
        "meta": {
          "batch": "2050001to2055000"
        }
      }
    },
    {
      "user_id": "50433820",
      "username": "111111167",
      "normalized_username": "111111167",
      "suspicion_score": 4,
      "patterns": {
        "ends_with_numbers": true,
        "contains_bot_keywords": false,
        "repeated_patterns": true,
        "sequential_numbers": false,
        "many_numbers": true,
        "special_word_combos": false,
        "generic_names": false,
        "consecutive_duplicates": true
      },
      "user_data": {
        "latest": {
          "rank": 2053785,
          "score": 3050,
          "username": "111111167",
          "level": 0,
          "id": 50433820,
          "friend_images": {
            "micro": "https://www.kogstatic.com/gen_cache/avatar_images/mrchen_18x18.jpg",
            "small": "https://www.kogstatic.com/gen_cache/avatar_images/mrchen_46x46.jpg",
            "medium": "https://www.kogstatic.com/gen_cache/avatar_images/mrchen_64x64.jpg",
            "large": "https://www.kogstatic.com/gen_cache/avatar_images/mrchen_330x451.jpg"
          },
          "is_subscriber": 0
        },
        "pages": [
          5135
        ],
        "meta": {
          "batch": "2050001to2055000"
        }
      }
    },
    {
      "user_id": "15726861",
      "username": "1111111457",
      "normalized_username": "1111111457",
      "suspicion_score": 4,
      "patterns": {
        "ends_with_numbers": true,
        "contains_bot_keywords": false,
        "repeated_patterns": true,
        "sequential_numbers": false,
        "many_numbers": true,
        "special_word_combos": false,
        "generic_names": false,
        "consecutive_duplicates": true
      },
      "user_data": {
        "latest": {
          "rank": 2065363,
          "score": 3030,
          "username": "1111111457",
          "level": 0,
          "id": 15726861,
          "friend_images": {
            "micro": "https://www.kogstatic.com/gen_cache/1e/4d/1e4dbf7e-69e6-4eff-9713-c44407423b03_18x18.jpg",
            "small": "https://www.kogstatic.com/gen_cache/1e/4d/1e4dbf7e-69e6-4eff-9713-c44407423b03_46x46.jpg",
            "medium": "https://www.kogstatic.com/gen_cache/1e/4d/1e4dbf7e-69e6-4eff-9713-c44407423b03_64x64.jpg",
            "large": "https://www.kogstatic.com/gen_cache/1e/4d/1e4dbf7e-69e6-4eff-9713-c44407423b03_330x451.jpg"
          },
          "is_subscriber": 0
        },
        "pages": [
          5164
        ],
        "meta": {
          "batch": "2065001to2070000"
        }
      }
    },
    {
      "user_id": "21148329",
      "username": "111111111122222233333",
      "normalized_username": "111111111122222233333",
      "suspicion_score": 4,
      "patterns": {
        "ends_with_numbers": true,
        "contains_bot_keywords": false,
        "repeated_patterns": true,
        "sequential_numbers": false,
        "many_numbers": true,
        "special_word_combos": false,
        "generic_names": false,
        "consecutive_duplicates": true
      },
      "user_data": {
        "latest": {
          "rank": 2068328,
          "score": 3021,
          "username": "111111111122222233333",
          "level": 0,
          "id": 21148329,
          "friend_images": {
            "micro": "https://www.kogstatic.com/gen_cache/avatar_images/panda_18x18.jpg",
            "small": "https://www.kogstatic.com/gen_cache/avatar_images/panda_46x46.jpg",
            "medium": "https://www.kogstatic.com/gen_cache/avatar_images/panda_64x64.jpg",
            "large": "https://www.kogstatic.com/gen_cache/avatar_images/panda_330x451.jpg"
          },
          "is_subscriber": 0
        },
        "pages": [
          5171
        ],
        "meta": {
          "batch": "2065001to2070000"
        }
      }
    },
    {
      "user_id": "22935059",
      "username": "111111112111111111",
      "normalized_username": "111111112111111111",
      "suspicion_score": 4,
      "patterns": {
        "ends_with_numbers": true,
        "contains_bot_keywords": false,
        "repeated_patterns": true,
        "sequential_numbers": false,
        "many_numbers": true,
        "special_word_combos": false,
        "generic_names": false,
        "consecutive_duplicates": true
      },
      "user_data": {
        "latest": {
          "rank": 2089677,
          "score": 2980,
          "username": "111111112111111111",
          "level": 0,
          "id": 22935059,
          "friend_images": {
            "micro": "https://www.kogstatic.com/gen_cache/14/6c/146cdb6f-147d-4a2c-8b81-98e0af9036be_18x18.jpg",
            "small": "https://www.kogstatic.com/gen_cache/14/6c/146cdb6f-147d-4a2c-8b81-98e0af9036be_46x46.jpg",
            "medium": "https://www.kogstatic.com/gen_cache/14/6c/146cdb6f-147d-4a2c-8b81-98e0af9036be_64x64.jpg",
            "large": "https://www.kogstatic.com/gen_cache/14/6c/146cdb6f-147d-4a2c-8b81-98e0af9036be_330x451.jpg"
          },
          "is_subscriber": 0
        },
        "pages": [
          5225
        ],
        "meta": {
          "batch": "2085001to2090000"
        }
      }
    },
    {
      "user_id": "50034936",
      "username": "11111111112233444",
      "normalized_username": "11111111112233444",
      "suspicion_score": 4,
      "patterns": {
        "ends_with_numbers": true,
        "contains_bot_keywords": false,
        "repeated_patterns": true,
        "sequential_numbers": false,
        "many_numbers": true,
        "special_word_combos": false,
        "generic_names": false,
        "consecutive_duplicates": true
      },
      "user_data": {
        "latest": {
          "rank": 2093008,
          "score": 2974,
          "username": "11111111112233444",
          "level": 0,
          "id": 50034936,
          "friend_images": {
            "micro": "https://www.kogstatic.com/placeholder/blockboy_micro_18x18.jpg",
            "small": "https://www.kogstatic.com/placeholder/blockboy_small_46x46.jpg",
            "medium": "https://www.kogstatic.com/placeholder/blockboy_medium_64x64.jpg",
            "large": "https://www.kogstatic.com/placeholder/blockboy_large_330x451.jpg"
          },
          "is_subscriber": 0
        },
        "pages": [
          5233
        ],
        "meta": {
          "batch": "2090001to2095000"
        }
      }
    },
    {
      "user_id": "17930548",
      "username": "11111111111111112223123425234",
      "normalized_username": "11111111111111112223123425234",
      "suspicion_score": 6,
      "patterns": {
        "ends_with_numbers": true,
        "contains_bot_keywords": false,
        "repeated_patterns": true,
        "sequential_numbers": true,
        "many_numbers": true,
        "special_word_combos": false,
        "generic_names": false,
        "consecutive_duplicates": true
      },
      "user_data": {
        "latest": {
          "rank": 2100820,
          "score": 2960,
          "username": "11111111111111112223123425234",
          "level": 0,
          "id": 17930548,
          "friend_images": {
            "micro": "https://www.kogstatic.com/placeholder/blockboy_micro_18x18.jpg",
            "small": "https://www.kogstatic.com/placeholder/blockboy_small_46x46.jpg",
            "medium": "https://www.kogstatic.com/placeholder/blockboy_medium_64x64.jpg",
            "large": "https://www.kogstatic.com/placeholder/blockboy_large_330x451.jpg"
          },
          "is_subscriber": 0
        },
        "pages": [
          5253
        ],
        "meta": {
          "batch": "2100001to2105000"
        }
      }
    },
    {
      "user_id": "22681474",
      "username": "111111++++",
      "normalized_username": "111111",
      "suspicion_score": 3,
      "patterns": {
        "ends_with_numbers": false,
        "contains_bot_keywords": false,
        "repeated_patterns": true,
        "sequential_numbers": false,
        "many_numbers": true,
        "special_word_combos": false,
        "generic_names": false,
        "consecutive_duplicates": true
      },
      "user_data": {
        "latest": {
          "rank": 2105299,
          "score": 2950,
          "username": "111111++++",
          "level": 0,
          "id": 22681474,
          "friend_images": {
            "micro": "https://www.kogstatic.com/placeholder/blockboy_micro_18x18.jpg",
            "small": "https://www.kogstatic.com/placeholder/blockboy_small_46x46.jpg",
            "medium": "https://www.kogstatic.com/placeholder/blockboy_medium_64x64.jpg",
            "large": "https://www.kogstatic.com/placeholder/blockboy_large_330x451.jpg"
          },
          "is_subscriber": 0
        },
        "pages": [
          5264
        ],
        "meta": {
          "batch": "2105001to2110000"
        }
      }
    }
  ]
}