{
  "count": 3,
  "accounts": [
    {
      "user_id": "22528977",
      "username": "12323232323232323232323",
      "normalized_username": "12323232323232323232323",
      "suspicion_score": 5,
      "patterns": {
        "ends_with_numbers": true,
        "contains_bot_keywords": false,
        "repeated_patterns": true,
        "sequential_numbers": true,
        "many_numbers": true,
        "special_word_combos": false,
        "generic_names": false,
        "consecutive_duplicates": false
      },
      "user_data": {
        "latest": {
          "rank": 2272165,
          "score": 2659,
          "username": "12323232323232323232323",
          "level": 0,
          "id": 22528977,
          "friend_images": {
            "micro": "https://www.kogstatic.com/gen_cache/20/65/2065ab47-54ac-4be2-8add-decedb4342c6_18x18.jpg",
            "small": "https://www.kogstatic.com/gen_cache/20/65/2065ab47-54ac-4be2-8add-decedb4342c6_46x46.jpg",
            "medium": "https://www.kogstatic.com/gen_cache/20/65/2065ab47-54ac-4be2-8add-decedb4342c6_64x64.jpg",
            "large": "https://www.kogstatic.com/gen_cache/20/65/2065ab47-54ac-4be2-8add-decedb4342c6_330x451.jpg"
          },
          "is_subscriber": 0
        },
        "pages": [
          5681
        ],
        "meta": {
          "batch": "2270001to2275000"
        }
      }
    },
    {
      "user_id": "19703307",
      "username": "123232245588",
      "normalized_username": "123232245588",
      "suspicion_score": 4,
      "patterns": {
        "ends_with_numbers": true,
        "contains_bot_keywords": false,
        "repeated_patterns": false,
        "sequential_numbers": true,
        "many_numbers": true,
        "special_word_combos": false,
        "generic_names": false,
        "consecutive_duplicates": false
      },
      "user_data": {
        "latest": {
          "rank": 2295154,
          "score": 2620,
          "username": "123232245588",
          "level": 0,
          "id": 19703307,
          "friend_images": {
            "micro": "https://www.kogstatic.com/gen_cache/avatar_images/kingoffire_18x18.jpg",
            "small": "https://www.kogstatic.com/gen_cache/avatar_images/kingoffire_46x46.jpg",
            "medium": "https://www.kogstatic.com/gen_cache/avatar_images/kingoffire_64x64.jpg",
            "large": "https://www.kogstatic.com/gen_cache/avatar_images/kingoffire_330x451.jpg"
          },
          "is_subscriber": 0
        },
        "pages": [
          5738
        ],
        "meta": {
          "batch": "2295001to2300000"
        }
      }
    },
    {
      "user_id": "667471731",
      "username": "1232323323222222222",
      "normalized_username": "1232323323222222222",
      "suspicion_score": 6,
      "patterns": {
        "ends_with_numbers": true,
        "contains_bot_keywords": false,
        "repeated_patterns": true,
        "sequential_numbers": true,
        "many_numbers": true,
        "special_word_combos": false,
        "generic_names": false,
        "consecutive_duplicates": true
      },
      "user_data": {
        "latest": {
          "rank": 2486100,
          "score": 2341,
          "username": "1232323323222222222",
          "level": 0,
          "id": 667471731,
          "friend_images": {
            "micro": "https://www.kogstatic.com/placeholder/blockboy_micro_18x18.jpg",
            "small": "https://www.kogstatic.com/placeholder/blockboy_small_46x46.jpg",
            "medium": "https://www.kogstatic.com/placeholder/blockboy_medium_64x64.jpg",
            "large": "https://www.kogstatic.com/placeholder/blockboy_large_330x451.jpg"
          },
          "is_subscriber": 0
        },
        "pages": [
          6216
        ],
        "meta": {
          "batch": "2485001to2490000"
        }
      }
    }
  ]
}